{"projectdata":{"isscored":false,"activityId":"https://cenariovr.com/11/9","name":"House Tour 6_21","cmi5":false,"publishDate":"2019-09-23T19:05:37Z","scorm":false,"description":"Basic Nav around a House","xapi":false,"nextObjId":40,"xAPIActID":"https://cenariovr.com/11/9","trial":false,"version":1,"lrsEndpoint":"https://cloud.scorm.com/tc/PD6GZ9LLKG/","lrsUser":"qvbNDjVioEdCce-2eO0","lrsPassword":"d7cHjvrMM20dn9DQzbE","fontsToLoad":["Roboto"]},"scenes":[{"image":"scene/4ba84774-2569-479a-9e3e-34600c0c6859.jpg","assetId":"0e67b7e9-5504-4dfd-8f6e-c0b30618ecd0","loop":false,"objects":[{"visible":true,"origHeight":0.2715,"distance":1,"src":null,"bTrans":false,"type":"hotspot","yaw":106.2665470848682,"assetId":-6,"name":"Arrow Up","width":0.13301607843478788,"assetName":"Arrow Up","id":"26","origWidth":0.2715,"pitch":-6.740772445283599,"actions":[{"action":"link","conditions":null,"target":"5"}],"height":0.13301607843478783,"effects":{"opacity":{"opacity":0.64}}}],"name":"master_bed","actionsShow":[{"action":null,"conditions":null,"target":null}],"id":"1","actions":[{"action":null,"conditions":null,"target":null}],"duration":60000},{"image":"scene/19eb32d2-77c4-49c1-af5f-ccdf34aabff3.jpg","assetId":"b0ce8d19-6669-40c7-affe-3de2bcf9a892","loop":false,"objects":[{"visible":true,"origHeight":0.2715,"distance":1,"src":null,"bTrans":false,"type":"hotspot","yaw":-159.1688122667876,"assetId":-3,"name":"Arrow Down","width":0.15829501631540782,"assetName":"Arrow Down","id":"39","origWidth":0.2715,"pitch":-4.32501128202468,"actions":[{"action":"link","conditions":null,"target":"5"}],"height":0.15829501631540785,"effects":{"opacity":{"opacity":0.65}}}],"name":"white_room","actionsShow":[{"action":null,"conditions":null,"target":null}],"id":"2","actions":[{"action":null,"conditions":null,"target":null}]},{"image":"scene/4a894ba2-4223-477e-8c86-180a0dae9439.jpg","assetId":"cd2409f2-2792-4f58-9ff2-7c92a33d2037","loop":false,"objects":[{"visible":true,"origHeight":0.2715,"distance":1,"src":null,"bTrans":false,"type":"hotspot","yaw":-59.226201952983956,"assetId":-6,"name":"Arrow Up","width":0.19679665517626027,"assetName":"Arrow Up","id":"27","origWidth":0.2715,"pitch":-9.899773872173672,"actions":[{"action":"link","conditions":null,"target":"1"}],"height":0.19679665517626027,"rotation":0,"effects":{"opacity":{"opacity":0.65}}},{"visible":true,"origHeight":0.2715,"distance":1,"src":null,"bTrans":false,"type":"hotspot","yaw":115.10986137568631,"assetId":-6,"name":"Arrow Up 1","width":0.12693310353985854,"assetName":"Arrow Up","id":"28","origWidth":0.2715,"pitch":-8.791441205547228,"actions":[{"action":"link","conditions":null,"target":"2"}],"height":0.12693310353985857,"effects":{"opacity":{"opacity":0.65}}},{"visible":true,"origHeight":0.2715,"distance":1,"src":null,"bTrans":false,"type":"hotspot","yaw":58.92458440028121,"assetId":-3,"name":"Arrow Down","width":0.11101752042905275,"assetName":"Arrow Down","id":"29","origWidth":0.2715,"pitch":-8.791441205547228,"actions":[{"action":"link","conditions":null,"target":"8"}],"height":0.11101752042905275,"effects":{"opacity":{"opacity":0.65}}}],"name":"IMG_1223 Panorama_sphere","id":"5","actions":[{"action":null,"target":null,"conditions":null}],"actionsShow":[{"action":null,"target":null,"conditions":null}],"duration":60000,"default_yaw":90.65624999999984},{"image":"scene/004098df-d205-40c3-a49f-6d4ba07c0f18.jpg","assetId":"f4ab8e4e-9397-4f30-a630-bb4005b7fe61","loop":false,"objects":[{"visible":true,"origHeight":0.2715,"distance":1,"src":null,"bTrans":false,"type":"hotspot","yaw":-126.9783595515586,"assetId":-3,"name":"Arrow Down","width":0.13806212095041695,"assetName":"Arrow Down","id":"30","origWidth":0.2715,"pitch":8.576432599332009,"actions":[{"action":"link","conditions":null,"target":"5"}],"height":0.13806212095041695,"effects":{"opacity":{"opacity":0.66}}},{"visible":true,"origHeight":0.2715,"distance":1,"src":null,"bTrans":false,"type":"hotspot","yaw":-43.73888133194659,"assetId":-3,"name":"Arrow Down 1","width":0.1974341651886979,"assetName":"Arrow Down","id":"31","origWidth":0.2715,"pitch":-36.49048369052649,"actions":[{"action":"link","conditions":null,"target":"4"}],"height":0.197434165188698,"effects":{"opacity":{"opacity":0.65}}}],"name":"IMG_1577 Panorama_sphere","id":"8"},{"image":"scene/d938cf03-cc76-4108-9faf-7ac4c2cf963f.jpg","assetId":"9de706c9-88d1-4e7b-b261-0a8ad37330b3","loop":false,"objects":[{"visible":true,"origHeight":0.2715,"distance":1,"src":null,"bTrans":false,"type":"hotspot","yaw":110.03298181250896,"assetId":-3,"name":"Arrow Down","width":0.12690652235422464,"assetName":"Arrow Down","id":"32","origWidth":0.2715,"pitch":12.418111538250539,"actions":[{"action":"link","conditions":null,"target":"8"}],"height":0.12690652235422464,"effects":{"opacity":{"opacity":0.65}}},{"visible":true,"origHeight":0.2715,"distance":1,"src":null,"bTrans":false,"type":"hotspot","yaw":-120.55707437485694,"assetId":-3,"name":"Arrow Down 1","width":0.10809952676174947,"assetName":"Arrow Down","id":"33","origWidth":0.2715,"pitch":-25.48185101405407,"actions":[{"action":"link","conditions":null,"target":"7"}],"height":0.1080995267617495,"effects":{"opacity":{"opacity":0.65}}}],"name":"IMG_1067 Panorama_sphere","id":"4"},{"image":"scene/8d3bc1b8-1160-4c46-b360-48213cfc4cfc.jpg","assetId":"f4e0fe47-e520-46de-8fb6-602e543db12b","loop":false,"objects":[{"visible":true,"origHeight":0.2715,"distance":1,"src":null,"bTrans":false,"type":"hotspot","yaw":173.00946617639278,"assetId":-3,"name":"Arrow Down","width":0.13332470626910475,"assetName":"Arrow Down","id":"34","origWidth":0.2715,"pitch":27.609978891031442,"actions":[{"action":"link","conditions":null,"target":"4"}],"height":0.13332470626910473,"effects":{"opacity":{"opacity":0.65}}},{"visible":true,"origHeight":0.2715,"distance":1,"src":null,"bTrans":false,"type":"hotspot","yaw":-99.84226334067237,"assetId":-3,"name":"Arrow Down 1","width":0.1803559412703691,"assetName":"Arrow Down","id":"35","origWidth":0.2715,"pitch":-29.642247824234015,"actions":[{"action":"link","conditions":null,"target":"3"}],"height":0.1803559412703691,"effects":{"opacity":{"opacity":0.66}}}],"name":"IMG_1541 Panorama_sphere","id":"7","actions":[{"action":null,"target":null,"conditions":null}],"actionsShow":[{"action":null,"target":null,"conditions":null}],"duration":60000,"default_yaw":83.43750000000003},{"image":"scene/ba0596e4-2b23-4ca3-b114-34f0dbbd2f52.jpg","assetId":"b0231b6a-3ef9-4fe5-acb4-121485d3a957","loop":false,"objects":[{"visible":true,"origHeight":0.2715,"distance":1,"src":null,"bTrans":false,"type":"hotspot","yaw":-28.368287272158092,"assetId":-3,"name":"Arrow Down","width":0.11869524307636331,"assetName":"Arrow Down","id":"36","origWidth":0.2715,"pitch":21.46575426233677,"actions":[{"action":"link","conditions":null,"target":"7"}],"height":0.11869524307636328,"effects":{"opacity":{"opacity":0.65}}},{"visible":true,"origHeight":0.2715,"distance":1,"src":null,"bTrans":false,"type":"hotspot","yaw":22.01788516474648,"assetId":-3,"name":"Arrow Down 1","width":0.11869524307636331,"assetName":"Arrow Down","id":"37","origWidth":0.2715,"pitch":-7.265609337198823,"actions":[{"action":"link","conditions":null,"target":"6"}],"height":0.11869524307636332,"effects":{"opacity":{"opacity":0.65}}}],"name":"IMG_0908 Panorama_sphere","id":"3"},{"image":"scene/744a7192-a770-4493-ac5f-86e999c4194c.jpg","assetId":"ee73e362-ae71-4cac-8d09-f94900ff1460","loop":false,"objects":[{"visible":true,"origHeight":0.2715,"distance":1,"src":null,"bTrans":false,"type":"hotspot","yaw":-167.98338238750782,"assetId":-3,"name":"Arrow Down","width":0.14150501871730584,"assetName":"Arrow Down","id":"38","origWidth":0.2715,"pitch":-6.7302711643883155,"actions":[{"action":"link","conditions":null,"target":"3"}],"height":0.14150501871730586,"effects":{"opacity":{"opacity":0.65}}}],"name":"room1","actionsShow":[{"action":null,"conditions":null,"target":null}],"id":"6","actions":[{"action":null,"conditions":null,"target":null}]}]}